mms/__init__.py
mms/client.py
mms/forecast_ts_client.py
mms/helpers.py
mms/real_time_ts_client.py
mms/simulation_ts_client.py
mms/ts_client.py
mms/util/__init__.py
mms/util/helpers.py
tests/__init__.py
tests/__main__.py
tests/helpers.py
tests/test_configuration.py
tests/test_devices.py
tests/ts_reads/__init__.py
tests/ts_reads/json_reads.py
tests/ts_reads/narrow_reads.py
tests/ts_reads/test_data_reads.py
tests/ts_writes/__init__.py
tests/ts_writes/json_writes.py
tests/ts_writes/narrow_writes.py
time_metrics/__init__.py
time_metrics/client.py
pf_dre_database_client-0.4.14.dist-info/LICENSE
pf_dre_database_client-0.4.14.dist-info/METADATA
pf_dre_database_client-0.4.14.dist-info/WHEEL
pf_dre_database_client-0.4.14.dist-info/top_level.txt
pf_dre_database_client-0.4.14.dist-info/RECORD
