Metadata-Version: 2.1
Name: pf-dre-database-client
Version: 0.4.14
Summary: Main data API used by DRE and MMS Tools & Subsystems
Home-page: https://github.com/pypa/sampleproject
Author: Dominic Hains
Author-email: d.hains@uq.edu.au
License: UNKNOWN
Platform: UNKNOWN
Classifier: Programming Language :: Python :: 3.8
Classifier: Programming Language :: Python :: 3.7
Classifier: License :: OSI Approved :: GNU General Public License v3 or later (GPLv3+)
Classifier: Intended Audience :: Developers
Classifier: Operating System :: OS Independent
Requires-Python: >=3.7
Requires-Dist: psycopg2-binary (>=2.8.5)
Requires-Dist: pandas (>=1.1.0)
Requires-Dist: pytz
Requires-Dist: numpy
Requires-Dist: python-dotenv
Requires-Dist: astral (>=2.2)
Requires-Dist: boto3 (>=1.14.43)
